dmic/__init__.py
dmic/lalalalal.py
dmic-0.0.2.dist-info/LICENSE
dmic-0.0.2.dist-info/METADATA
dmic-0.0.2.dist-info/WHEEL
dmic-0.0.2.dist-info/entry_points.txt
dmic-0.0.2.dist-info/top_level.txt
dmic-0.0.2.dist-info/RECORD
