Metadata-Version: 2.1
Name: dmic
Version: 0.0.2
Summary: A Met Tool for file format conversion
Home-page: UNKNOWN
Author: Kasper Hintz
Author-email: kah@dmi.dk
License: UNKNOWN
Platform: UNKNOWN
Classifier: Programming Language :: Python :: 3
Classifier: License :: OSI Approved :: MIT License
Classifier: Operating System :: OS Independent
